lexical_quality/__init__.py
lexical_quality/coherence.py
lexical_quality/grammar_spelling.py
lexical_quality/main.py
lexical_quality/readability.py
lexical_quality/results.py
tests/__init__.py
tests/test_coherence.py
tests/test_grammar_spelling.py
tests/test_readability.py
lexical_quality-0.1.0.dist-info/METADATA
lexical_quality-0.1.0.dist-info/WHEEL
lexical_quality-0.1.0.dist-info/entry_points.txt
lexical_quality-0.1.0.dist-info/top_level.txt
lexical_quality-0.1.0.dist-info/RECORD
